[{"__type__":"cc.SpriteFrame","content":{"name":"menu_0003_3-拷贝-2","texture":"c6a8578a-66aa-493e-8fbd-8f4b908cd233","rect":[0,0,105,98],"offset":[0,0],"originalSize":[105,98]}},{"__type__":"cc.SpriteFrame","content":{"name":"menu_0008_背景","texture":"72910771-f099-4ebc-9d81-6702d33f6232","rect":[0,0,1366,766],"offset":[0,0],"originalSize":[1366,766]}},{"__type__":"cc.SpriteFrame","content":{"name":"menu_0004_3-拷贝-3","texture":"6ddbb593-df5f-4b32-adf7-52baf0140070","rect":[0,0,105,98],"offset":[0,0],"originalSize":[105,98]}},{"__type__":"cc.SpriteFrame","content":{"name":"menu_0006_3-副本","texture":"5c40e9a9-71f5-4f21-880c-2432c527eb58","rect":[0,0,676,144],"offset":[0,0],"originalSize":[676,144]}},[{"__type__":"cc.SceneAsset","_name":"start","scene":{"__id__":1},"asyncLoadAssets":false},{"__type__":"cc.Scene","_anchorPoint":{"__type__":"cc.Vec2"},"_children":[{"__id__":2}],"autoReleaseAssets":false},{"__type__":"cc.Node","_name":"Canvas","_parent":{"__id__":1},"_contentSize":{"__type__":"cc.Size","width":480,"height":320},"_children":[{"__id__":3},{"__id__":4},{"__id__":5},{"__id__":6},{"__id__":7}],"_position":{"__type__":"cc.Vec2","x":240,"y":160},"_id":"a130b0UeSxCmYCoI7F2WsZz","_components":[{"__type__":"cc.Canvas","node":{"__id__":2},"_designResolution":{"__type__":"cc.Size","width":480,"height":320}},{"__type__":"280c3rsZJJKnZ9RqbALVwtK","node":{"__id__":2}},{"__type__":"280c3rsZJJKnZ9RqbALVwtK","node":{"__id__":2}}]},{"__type__":"cc.Node","_name":"background","_parent":{"__id__":2},"_contentSize":{"__type__":"cc.Size","width":480,"height":320},"_components":[{"__type__":"cc.Sprite","node":{"__id__":3},"_spriteFrame":{"__uuid__":"7fccaac7-87de-450c-a1fd-091977128866"},"_sizeMode":0}]},{"__type__":"cc.Node","_name":"close","_parent":{"__id__":2},"_contentSize":{"__type__":"cc.Size","width":40,"height":40},"_scaleX":1.04,"_scaleY":1.04,"_position":{"__type__":"cc.Vec2","x":209.1,"y":131.7},"_components":[{"__type__":"cc.Sprite","node":{"__id__":4},"_spriteFrame":{"__uuid__":"26e81830-1393-4f74-a5fb-f80a4f5ad736"},"_type":1,"_sizeMode":0},{"__type__":"cc.Button","node":{"__id__":4},"transition":2,"pressedColor":{"__type__":"cc.Color","r":255,"g":255,"b":255},"pressedSprite":{"__uuid__":"26e81830-1393-4f74-a5fb-f80a4f5ad736"},"hoverSprite":{"__uuid__":"26e81830-1393-4f74-a5fb-f80a4f5ad736"},"clickEvents":[{"__type__":"cc.ClickEvent","target":{"__id__":2},"component":"start","handler":"end"}],"_N$normalColor":{"__type__":"cc.Color","r":255,"g":255,"b":255},"_N$disabledColor":{"__type__":"cc.Color","r":255,"g":255,"b":255},"_N$normalSprite":{"__uuid__":"26e81830-1393-4f74-a5fb-f80a4f5ad736"},"_N$disabledSprite":{"__uuid__":"29158224-f8dd-4661-a796-1ffab537140e"},"_N$target":{"__id__":4}},null]},{"__type__":"cc.Node","_name":"question","_parent":{"__id__":2},"_contentSize":{"__type__":"cc.Size","width":40,"height":40},"_position":{"__type__":"cc.Vec2","x":161.9,"y":132.1},"_components":[{"__type__":"cc.Sprite","node":{"__id__":5},"_spriteFrame":{"__uuid__":"7ca424d8-edd9-4625-a125-644864e48e4b"},"_type":1,"_sizeMode":0},{"__type__":"cc.Button","node":{"__id__":5},"transition":2,"pressedColor":{"__type__":"cc.Color","r":255,"g":255,"b":255},"pressedSprite":{"__uuid__":"7ca424d8-edd9-4625-a125-644864e48e4b"},"hoverSprite":{"__uuid__":"7ca424d8-edd9-4625-a125-644864e48e4b"},"_N$normalColor":{"__type__":"cc.Color","r":255,"g":255,"b":255},"_N$disabledColor":{"__type__":"cc.Color","r":255,"g":255,"b":255},"_N$normalSprite":{"__uuid__":"7ca424d8-edd9-4625-a125-644864e48e4b"},"_N$disabledSprite":{"__uuid__":"29158224-f8dd-4661-a796-1ffab537140e"},"_N$target":{"__id__":5}}]},{"__type__":"cc.Node","_name":"start","_parent":{"__id__":2},"_contentSize":{"__type__":"cc.Size","width":262,"height":54.8},"_position":{"__type__":"cc.Vec2","x":102.9,"y":-93.5},"_components":[{"__type__":"cc.Sprite","node":{"__id__":6},"_spriteFrame":{"__uuid__":"bbde2fcf-fd87-4449-a791-c3367a4f6bc8"},"_type":1,"_sizeMode":0},{"__type__":"cc.Button","node":{"__id__":6},"transition":2,"pressedColor":{"__type__":"cc.Color","r":255,"g":255,"b":255},"pressedSprite":{"__uuid__":"c8bf689f-a23d-4a74-b998-926586b7da17"},"hoverSprite":{"__uuid__":"d7a6beff-4df0-4654-8fe4-b441e0beb833"},"clickEvents":[{"__type__":"cc.ClickEvent","target":{"__id__":2},"component":"start","handler":"go_home"}],"_N$normalColor":{"__type__":"cc.Color","r":255,"g":255,"b":255},"_N$disabledColor":{"__type__":"cc.Color","r":255,"g":255,"b":255},"_N$normalSprite":{"__uuid__":"bbde2fcf-fd87-4449-a791-c3367a4f6bc8"},"_N$disabledSprite":{"__uuid__":"29158224-f8dd-4661-a796-1ffab537140e"},"_N$target":{"__id__":6}}]},{"__type__":"cc.Node","_name":"good","_parent":{"__id__":2},"_contentSize":{"__type__":"cc.Size","width":118.6,"height":27.7},"_position":{"__type__":"cc.Vec2","x":106.2,"y":-141.9},"_components":[{"__type__":"cc.Sprite","node":{"__id__":7},"_spriteFrame":{"__uuid__":"16b70ae4-d4a3-4274-8261-079ffe968cc3"},"_type":1,"_sizeMode":0},{"__type__":"cc.Button","node":{"__id__":7},"transition":2,"pressedColor":{"__type__":"cc.Color","r":255,"g":255,"b":255},"pressedSprite":{"__uuid__":"6596b822-e953-4479-bc1a-61f3bfc3287d"},"hoverSprite":{"__uuid__":"e3bb8c00-43ab-41fc-becf-da68faf0e7c2"},"_N$normalColor":{"__type__":"cc.Color","r":255,"g":255,"b":255},"_N$disabledColor":{"__type__":"cc.Color","r":255,"g":255,"b":255},"_N$normalSprite":{"__uuid__":"16b70ae4-d4a3-4274-8261-079ffe968cc3"},"_N$disabledSprite":{"__uuid__":"29158224-f8dd-4661-a796-1ffab537140e"},"_N$target":{"__id__":7}}]}],{"__type__":"cc.SpriteFrame","content":{"name":"menu_0007_3","texture":"ee4753bf-ca85-4539-a63a-b6273fbdbd49","rect":[0,0,676,144],"offset":[0,0],"originalSize":[676,144]}},{"__type__":"cc.SpriteFrame","content":{"name":"menu_0005_3-副本-2","texture":"1e57dd8d-8f1d-469e-b7ef-d7f1403467f6","rect":[0,0,676,144],"offset":[0,0],"originalSize":[676,144]}},{"__type__":"cc.SpriteFrame","content":{"name":"menu_0002_12-拷贝-2","texture":"de39b09e-15fd-4381-b5e7-06d8a9ee899d","rect":[0,0,304,71],"offset":[0,0],"originalSize":[304,71]}},{"__type__":"cc.SpriteFrame","content":{"name":"menu_0001_12-拷贝-22","texture":"7a2d63be-caa6-4bfa-95a1-4158d379443d","rect":[0,0,304,71],"offset":[0,0],"originalSize":[304,71]}},{"__type__":"cc.SpriteFrame","content":{"name":"menu_0000_12-拷贝-21","texture":"9a82bfd0-248d-46e2-9170-ac38e7525c06","rect":[0,0,304,71],"offset":[0,0],"originalSize":[304,71]}}]